deel_sdk/__init__.py
deel_sdk/api_client.py
deel_sdk/api_response.py
deel_sdk/configuration.py
deel_sdk/exceptions.py
deel_sdk/py.typed
deel_sdk/rest.py
deel_sdk/api/__init__.py
deel_sdk/api/contracts_api.py
deel_sdk/models/__init__.py
deel_sdk/models/api_error.py
deel_sdk/models/api_error_container.py
deel_sdk/models/api_error_request.py
deel_sdk/models/get_contract_list200_response.py
deel_sdk/models/get_contract_list200_response_data_inner.py
deel_sdk/models/get_contract_list200_response_data_inner_client.py
deel_sdk/models/get_contract_list200_response_data_inner_client_team.py
deel_sdk/models/get_contract_list200_response_data_inner_invitations.py
deel_sdk/models/get_contract_list200_response_data_inner_signatures.py
deel_sdk/models/get_contract_list200_response_data_inner_worker.py
deel_sdk/models/get_contract_list200_response_data_inner_worker_alternate_email_inner.py
deel_sdk/models/get_contract_list200_response_page.py
deel_sdk/models/get_contract_list_currencies_parameter.py
deel_sdk-2.1.51.dist-info/METADATA
deel_sdk-2.1.51.dist-info/WHEEL
deel_sdk-2.1.51.dist-info/top_level.txt
deel_sdk-2.1.51.dist-info/RECORD
