Metadata-Version: 2.2
Name: deel-sdk
Version: 2.1.51
Summary: Deel REST API
Home-page: 
Author: Deel API Team
Author-email: apiteam@deel.com
Keywords: OpenAPI,OpenAPI-Generator,Deel REST API
Requires-Dist: urllib3<3.0.0,>=1.25.3
Requires-Dist: python-dateutil>=2.8.2
Requires-Dist: pydantic>=2
Requires-Dist: typing-extensions>=4.7.1
Dynamic: author
Dynamic: author-email
Dynamic: description
Dynamic: description-content-type
Dynamic: keywords
Dynamic: requires-dist
Dynamic: summary
